pyfq/__init__.py
pyfq/pyfq.py
pyfq/core/__init__.py
pyfq/core/catfq.py
pyfq/core/qcfq.py
pyfq/examples/SP1.fq
pyfq/examples/SP1.fq.gz
pyfq/examples/__init__.py
pyfq/test/__init__.py
pyfq/utils/__init__.py
pyfq/utils/catfq.py
pyfq/utils/fastq.py
pyfq-0.0.6.dist-info/DESCRIPTION.rst
pyfq-0.0.6.dist-info/METADATA
pyfq-0.0.6.dist-info/RECORD
pyfq-0.0.6.dist-info/WHEEL
pyfq-0.0.6.dist-info/entry_points.txt
pyfq-0.0.6.dist-info/metadata.json
pyfq-0.0.6.dist-info/top_level.txt
